{
  "schemaVersion": "1",
  "generatedAt": "2026-04-22T20:06:55.804Z",
  "patientId": "GUADALUPE_SANTILLANES__7dff81c9298ebad6",
  "batchId": "batch-meadows-home-health-2026-04-22T19-20-51-707Z-032ca5da",
  "factPack": {
    "documentType": "oasis",
    "diagnoses": [
      {
        "description": "Diagnosis",
        "source": "📄 Santillanes sx order.pdf 📝 ✏️ 🗑️ 🔗"
      },
      {
        "code": "M79.671",
        "description": "M79.671",
        "source": "📄 Santillanes sx order.pdf 📝 ✏️ 🗑️ 🔗"
      },
      {
        "code": "M79.671",
        "description": "Diagnosis: Foot Pain, Right -",
        "source": "📄 Santillanes sx order.pdf 📝 ✏️ 🗑️ 🔗"
      },
      {
        "code": "M21.6X1",
        "description": "Instructions: 28250- , 29893- , 28120- , 28003-",
        "source": "📄 Santillanes sx order.pdf 📝 ✏️ 🗑️ 🔗"
      },
      {
        "code": "M72.2",
        "description": "Instructions: 28250- , 29893- , 28120- , 28003-",
        "source": "📄 Santillanes sx order.pdf 📝 ✏️ 🗑️ 🔗"
      },
      {
        "code": "M77.31",
        "description": "Instructions: 28250- , 29893- , 28120- , 28003-",
        "source": "📄 Santillanes sx order.pdf 📝 ✏️ 🗑️ 🔗"
      },
      {
        "code": "L03.116",
        "description": "Instructions: 28250- , 29893- , 28120- , 28003-",
        "source": "📄 Santillanes sx order.pdf 📝 ✏️ 🗑️ 🔗"
      },
      {
        "code": "I00",
        "description": "Diagnosis code candidate from extracted document metadata",
        "source": "OASIS documents page"
      },
      {
        "code": "I25",
        "description": "Diagnosis code candidate from extracted document metadata",
        "source": "OASIS documents page"
      },
      {
        "code": "I50",
        "description": "Diagnosis code candidate from extracted document metadata",
        "source": "OASIS documents page"
      },
      {
        "code": "M79.671",
        "description": "Diagnosis code candidate from extracted document metadata",
        "source": "📄 Santillanes sx order.pdf 📝 ✏️ 🗑️ 🔗"
      },
      {
        "code": "M21.6X1",
        "description": "Diagnosis code candidate from extracted document metadata",
        "source": "📄 Santillanes sx order.pdf 📝 ✏️ 🗑️ 🔗"
      }
    ],
    "medications": [],
    "allergies": [],
    "homeboundEvidence": [
      {
        "field": "homebound",
        "text": "DME Preauthorization 1: Cam Walker Boot L4361",
        "source": "📄 Santillanes sx order.pdf 📝 ✏️ 🗑️ 🔗"
      }
    ],
    "skilledNeedEvidence": [],
    "hospitalizationReasons": [
      {
        "field": "hospitalization_reason",
        "text": "Perform at: Henderson Hospital",
        "source": "📄 Santillanes sx order.pdf 📝 ✏️ 🗑️ 🔗"
      },
      {
        "field": "hospitalization_reason",
        "text": "Other Labs/Tests: Labs to be done at Henderson Hospital",
        "source": "📄 Santillanes sx order.pdf 📝 ✏️ 🗑️ 🔗"
      }
    ],
    "assessmentValues": [
      {
        "field": "assessment_value",
        "text": "Pain in right foot",
        "source": "📄 Santillanes sx order.pdf 📝 ✏️ 🗑️ 🔗"
      },
      {
        "field": "assessment_value",
        "text": "Diagnosis: Foot Pain, Right - M79.671",
        "source": "📄 Santillanes sx order.pdf 📝 ✏️ 🗑️ 🔗"
      }
    ],
    "uncategorizedEvidence": [],
    "stats": {
      "rawCharacters": 5109,
      "packedCharacters": 793,
      "reductionPercent": 84.5
    }
  }
}