{
  "primaryDiagnosis": {
    "code": "",
    "description": "muscle weakness",
    "confidence": "medium"
  },
  "otherDiagnoses": [
    {
      "code": "",
      "description": "719.46) Pain in left knee started 22 - Z71.89 Advance directive discussed with patient (finding) (",
      "confidence": "medium"
    },
    {
      "code": "",
      "description": "deformities, admits muscle weakness",
      "confidence": "medium"
    },
    {
      "code": "",
      "description": "780.79) Weakness modified 25 Jun, 2023 - to qualify",
      "confidence": "medium"
    },
    {
      "code": "",
      "description": "reports minimal pain",
      "confidence": "medium"
    },
    {
      "code": "",
      "description": "knee pain.",
      "confidence": "medium"
    },
    {
      "code": "",
      "description": "Cardiovascular: Denies chest pain, palpitations, dizziness, syncope, edema.",
      "confidence": "medium"
    },
    {
      "code": "",
      "description": "abdominal pain",
      "confidence": "medium"
    }
  ],
  "suggestedOnsetType": "onset",
  "suggestedSeverity": 1,
  "comorbidityFlags": {
    "pvd_pad": false,
    "diabetes": false,
    "none": true
  },
  "notes": [
    "Ordered services: Skilled Nursing, Physical Therapy, Occupational Therapy",
    "Primary diagnosis code left blank because no explicit or strongly inferable ICD-10 mapping was retained."
  ]
}