[
  {
    "sectionName": "patient_identity",
    "extractedTextSpans": [
      "Patient Name: Gloria Allen",
      "DOB: 8/21/51",
      "GLORIAALLEN (DOB: 8/21/1951, F)",
      "ALLEN, GLORIA (DOB: 8/21/1951 ID: 23282) F",
      "ALLEN, GLORIA (DOB: 8/21/1951 ID: 23282) F",
      "Neurology Resident, PGY-3",
      "ALLEN, GLORIA (DOB: 8/21/1951 ID: 23282) F"
    ],
    "normalizedSummary": "Patient Name: Gloria Allen DOB: 8/21/51 GLORIAALLEN (DOB: 8/21/1951, F)",
    "confidence": 1,
    "lineReferences": [
      {
        "lineStart": 9,
        "lineEnd": 9,
        "charStart": 121,
        "charEnd": 147
      },
      {
        "lineStart": 12,
        "lineEnd": 12,
        "charStart": 193,
        "charEnd": 205
      },
      {
        "lineStart": 64,
        "lineEnd": 64,
        "charStart": 1271,
        "charEnd": 1302
      },
      {
        "lineStart": 103,
        "lineEnd": 103,
        "charStart": 2273,
        "charEnd": 2315
      },
      {
        "lineStart": 176,
        "lineEnd": 176,
        "charStart": 4707,
        "charEnd": 4749
      },
      {
        "lineStart": 233,
        "lineEnd": 233,
        "charStart": 6751,
        "charEnd": 6776
      },
      {
        "lineStart": 243,
        "lineEnd": 243,
        "charStart": 7120,
        "charEnd": 7162
      }
    ]
  },
  {
    "sectionName": "referral_metadata",
    "extractedTextSpans": [
      "Reason for Referral: OT FOR Hand / finger stiffness"
    ],
    "normalizedSummary": "Reason for Referral: OT FOR Hand / finger stiffness",
    "confidence": 0.55,
    "lineReferences": [
      {
        "lineStart": 32,
        "lineEnd": 32,
        "charStart": 576,
        "charEnd": 627
      }
    ]
  },
  {
    "sectionName": "medications",
    "extractedTextSpans": [
      "Allergies"
    ],
    "normalizedSummary": "Allergies",
    "confidence": 0.55,
    "lineReferences": [
      {
        "lineStart": 163,
        "lineEnd": 163,
        "charStart": 4307,
        "charEnd": 4316
      }
    ]
  },
  {
    "sectionName": "functional_limitations",
    "extractedTextSpans": [
      "Pt denies experiencing any weakness on her hands, denies dropping any"
    ],
    "normalizedSummary": "Pt denies experiencing any weakness on her hands, denies dropping any",
    "confidence": 0.55,
    "lineReferences": [
      {
        "lineStart": 137,
        "lineEnd": 137,
        "charStart": 3587,
        "charEnd": 3656
      }
    ]
  },
  {
    "sectionName": "therapy_need",
    "extractedTextSpans": [
      "occupational therapy for hand fingers stiffness (fingers getting stuck) and lumbar"
    ],
    "normalizedSummary": "occupational therapy for hand fingers stiffness (fingers getting stuck) and lumbar",
    "confidence": 0.55,
    "lineReferences": [
      {
        "lineStart": 228,
        "lineEnd": 228,
        "charStart": 6542,
        "charEnd": 6624
      }
    ]
  },
  {
    "sectionName": "other_clinical_notes",
    "extractedTextSpans": [
      "Notes: 1/26/26 - active thru cmd - cr",
      "Notes: 1/26/26 - active thru cmd - cr",
      "Plan printed and provided to patient:"
    ],
    "normalizedSummary": "Notes: 1/26/26 - active thru cmd - cr Notes: 1/26/26 - active thru cmd - cr Plan printed and provided to patient:",
    "confidence": 0.95,
    "lineReferences": [
      {
        "lineStart": 81,
        "lineEnd": 81,
        "charStart": 1626,
        "charEnd": 1663
      },
      {
        "lineStart": 88,
        "lineEnd": 88,
        "charStart": 1817,
        "charEnd": 1854
      },
      {
        "lineStart": 223,
        "lineEnd": 223,
        "charStart": 6286,
        "charEnd": 6323
      }
    ]
  }
]