[
  {
    "sectionName": "patient_identity",
    "extractedTextSpans": [
      "Patient Name: Briggs, Aurora,",
      "DOB: 08/13/1942, Account No: 113504",
      "Patient Name:",
      "DOB:",
      "DOB:",
      "DOB:",
      "Patient Name: Briggs, Aurora,",
      "DOB: 08/13/1942, Account No: 113504",
      "Patient Name: Briggs, Aurora,",
      "DOB: 08/13/1942, Account No: 113504",
      "DOB: 08/13/1942",
      "Patient Name: Briggs, Aurora,",
      "DOB: 08/13/1942, Account No: 113504",
      "Patient Name: Briggs, Aurora,",
      "DOB: 08/13/1942, Account No: 113504",
      "Patient Name: Briggs, Aurora,",
      "DOB: 08/13/1942, Account No: 113504",
      "Patient Name: Briggs, Aurora,",
      "DOB: 08/13/1942, Account No: 113504",
      "Patient Name: Briggs, Aurora,",
      "DOB: 08/13/1942, Account No: 113504",
      "DOB: 08/13/1942 Age: 83 Y Sex: female",
      "Patient Name: Briggs, Aurora,",
      "DOB: 08/13/1942, Account No: 113504",
      "Patient Name: Briggs, Aurora,",
      "DOB: 08/13/1942, Account No: 113504",
      "Patient Name: Briggs, Aurora,",
      "DOB: 08/13/1942, Account No: 113504",
      "Patient Name: Briggs, Aurora,",
      "DOB: 08/13/1942, Account No: 113504",
      "Patient Name: Briggs, Aurora,",
      "DOB: 08/13/1942, Account No: 113504"
    ],
    "normalizedSummary": "Patient Name: Briggs, Aurora, DOB: 08/13/1942, Account No: 113504 Patient Name:",
    "confidence": 1,
    "lineReferences": [
      {
        "lineStart": 35,
        "lineEnd": 35,
        "charStart": 896,
        "charEnd": 925
      },
      {
        "lineStart": 36,
        "lineEnd": 36,
        "charStart": 926,
        "charEnd": 961
      },
      {
        "lineStart": 48,
        "lineEnd": 48,
        "charStart": 1192,
        "charEnd": 1205
      },
      {
        "lineStart": 51,
        "lineEnd": 51,
        "charStart": 1230,
        "charEnd": 1234
      },
      {
        "lineStart": 67,
        "lineEnd": 67,
        "charStart": 1573,
        "charEnd": 1577
      },
      {
        "lineStart": 79,
        "lineEnd": 79,
        "charStart": 1832,
        "charEnd": 1836
      },
      {
        "lineStart": 113,
        "lineEnd": 113,
        "charStart": 2418,
        "charEnd": 2447
      },
      {
        "lineStart": 114,
        "lineEnd": 114,
        "charStart": 2448,
        "charEnd": 2483
      },
      {
        "lineStart": 161,
        "lineEnd": 161,
        "charStart": 3349,
        "charEnd": 3378
      },
      {
        "lineStart": 162,
        "lineEnd": 162,
        "charStart": 3379,
        "charEnd": 3414
      },
      {
        "lineStart": 166,
        "lineEnd": 166,
        "charStart": 3463,
        "charEnd": 3478
      },
      {
        "lineStart": 278,
        "lineEnd": 278,
        "charStart": 6657,
        "charEnd": 6686
      },
      {
        "lineStart": 279,
        "lineEnd": 279,
        "charStart": 6687,
        "charEnd": 6722
      },
      {
        "lineStart": 407,
        "lineEnd": 407,
        "charStart": 10862,
        "charEnd": 10891
      },
      {
        "lineStart": 408,
        "lineEnd": 408,
        "charStart": 10892,
        "charEnd": 10927
      },
      {
        "lineStart": 530,
        "lineEnd": 530,
        "charStart": 14653,
        "charEnd": 14682
      },
      {
        "lineStart": 531,
        "lineEnd": 531,
        "charStart": 14683,
        "charEnd": 14718
      },
      {
        "lineStart": 619,
        "lineEnd": 619,
        "charStart": 16656,
        "charEnd": 16685
      },
      {
        "lineStart": 620,
        "lineEnd": 620,
        "charStart": 16686,
        "charEnd": 16721
      },
      {
        "lineStart": 684,
        "lineEnd": 684,
        "charStart": 17905,
        "charEnd": 17934
      },
      {
        "lineStart": 685,
        "lineEnd": 685,
        "charStart": 17935,
        "charEnd": 17970
      },
      {
        "lineStart": 692,
        "lineEnd": 692,
        "charStart": 18075,
        "charEnd": 18112
      },
      {
        "lineStart": 787,
        "lineEnd": 787,
        "charStart": 19926,
        "charEnd": 19955
      },
      {
        "lineStart": 788,
        "lineEnd": 788,
        "charStart": 19956,
        "charEnd": 19991
      },
      {
        "lineStart": 909,
        "lineEnd": 909,
        "charStart": 22236,
        "charEnd": 22265
      },
      {
        "lineStart": 910,
        "lineEnd": 910,
        "charStart": 22266,
        "charEnd": 22301
      },
      {
        "lineStart": 983,
        "lineEnd": 983,
        "charStart": 25384,
        "charEnd": 25413
      },
      {
        "lineStart": 984,
        "lineEnd": 984,
        "charStart": 25414,
        "charEnd": 25449
      },
      {
        "lineStart": 1048,
        "lineEnd": 1048,
        "charStart": 30482,
        "charEnd": 30511
      },
      {
        "lineStart": 1049,
        "lineEnd": 1049,
        "charStart": 30512,
        "charEnd": 30547
      },
      {
        "lineStart": 1187,
        "lineEnd": 1187,
        "charStart": 32412,
        "charEnd": 32441
      },
      {
        "lineStart": 1188,
        "lineEnd": 1188,
        "charStart": 32442,
        "charEnd": 32477
      }
    ]
  },
  {
    "sectionName": "referral_metadata",
    "extractedTextSpans": [
      "REFERRAL",
      "Referral From Information:",
      "Referral To Information:",
      "REFERRAL",
      "Reason For Referral:",
      "Referral To:Home Health Care",
      "Referral From",
      "Referral To",
      "send referral there to continue with"
    ],
    "normalizedSummary": "REFERRAL Referral From Information: Referral To Information:",
    "confidence": 1,
    "lineReferences": [
      {
        "lineStart": 37,
        "lineEnd": 37,
        "charStart": 962,
        "charEnd": 970
      },
      {
        "lineStart": 86,
        "lineEnd": 86,
        "charStart": 1923,
        "charEnd": 1949
      },
      {
        "lineStart": 107,
        "lineEnd": 107,
        "charStart": 2256,
        "charEnd": 2280
      },
      {
        "lineStart": 128,
        "lineEnd": 128,
        "charStart": 2665,
        "charEnd": 2673
      },
      {
        "lineStart": 136,
        "lineEnd": 136,
        "charStart": 2857,
        "charEnd": 2877
      },
      {
        "lineStart": 387,
        "lineEnd": 387,
        "charStart": 10175,
        "charEnd": 10203
      },
      {
        "lineStart": 1273,
        "lineEnd": 1273,
        "charStart": 33300,
        "charEnd": 33313
      },
      {
        "lineStart": 1274,
        "lineEnd": 1274,
        "charStart": 33314,
        "charEnd": 33325
      },
      {
        "lineStart": 1295,
        "lineEnd": 1295,
        "charStart": 33678,
        "charEnd": 33714
      }
    ]
  },
  {
    "sectionName": "referring_provider",
    "extractedTextSpans": [
      "Provider NPI:",
      "Provider NPI:",
      "Provider NPI:"
    ],
    "normalizedSummary": "Provider NPI: Provider NPI: Provider NPI:",
    "confidence": 0.95,
    "lineReferences": [
      {
        "lineStart": 92,
        "lineEnd": 92,
        "charStart": 2016,
        "charEnd": 2029
      },
      {
        "lineStart": 116,
        "lineEnd": 116,
        "charStart": 2499,
        "charEnd": 2512
      },
      {
        "lineStart": 156,
        "lineEnd": 156,
        "charStart": 3146,
        "charEnd": 3159
      }
    ]
  },
  {
    "sectionName": "diagnoses",
    "extractedTextSpans": [
      "Diagnosis:",
      "Diagnosis"
    ],
    "normalizedSummary": "Diagnosis: Diagnosis",
    "confidence": 0.75,
    "lineReferences": [
      {
        "lineStart": 141,
        "lineEnd": 141,
        "charStart": 2973,
        "charEnd": 2983
      },
      {
        "lineStart": 1119,
        "lineEnd": 1119,
        "charStart": 31675,
        "charEnd": 31684
      }
    ]
  },
  {
    "sectionName": "medications",
    "extractedTextSpans": [
      "Medication Refill",
      "Well controlled with medication.",
      "Well controlled with medication, see vital signs.",
      "Patient requesting for fills on medication,",
      "pharmacy and",
      "Medication List reviewed and reconciled",
      "1159F MEDICATION LIST DOCD IN MEDI",
      "Allergies",
      "Allergies"
    ],
    "normalizedSummary": "Medication Refill Well controlled with medication. Well controlled with medication, see vital signs.",
    "confidence": 1,
    "lineReferences": [
      {
        "lineStart": 182,
        "lineEnd": 182,
        "charStart": 3820,
        "charEnd": 3837
      },
      {
        "lineStart": 246,
        "lineEnd": 246,
        "charStart": 5582,
        "charEnd": 5614
      },
      {
        "lineStart": 283,
        "lineEnd": 283,
        "charStart": 6784,
        "charEnd": 6833
      },
      {
        "lineStart": 432,
        "lineEnd": 432,
        "charStart": 11575,
        "charEnd": 11618
      },
      {
        "lineStart": 435,
        "lineEnd": 435,
        "charStart": 11700,
        "charEnd": 11712
      },
      {
        "lineStart": 494,
        "lineEnd": 494,
        "charStart": 13624,
        "charEnd": 13663
      },
      {
        "lineStart": 505,
        "lineEnd": 505,
        "charStart": 13947,
        "charEnd": 13981
      },
      {
        "lineStart": 594,
        "lineEnd": 594,
        "charStart": 16189,
        "charEnd": 16198
      },
      {
        "lineStart": 704,
        "lineEnd": 704,
        "charStart": 18347,
        "charEnd": 18356
      }
    ]
  },
  {
    "sectionName": "functional_limitations",
    "extractedTextSpans": [
      "fatigue, malaise, numbness/weakness, tingling, dizziness,"
    ],
    "normalizedSummary": "fatigue, malaise, numbness/weakness, tingling, dizziness,",
    "confidence": 0.55,
    "lineReferences": [
      {
        "lineStart": 446,
        "lineEnd": 446,
        "charStart": 12003,
        "charEnd": 12060
      }
    ]
  },
  {
    "sectionName": "therapy_need",
    "extractedTextSpans": [
      "Physical therapy"
    ],
    "normalizedSummary": "Physical therapy",
    "confidence": 0.55,
    "lineReferences": [
      {
        "lineStart": 1294,
        "lineEnd": 1294,
        "charStart": 33661,
        "charEnd": 33677
      }
    ]
  },
  {
    "sectionName": "other_clinical_notes",
    "extractedTextSpans": [
      "Progress Note",
      "Progress Note: Ngoc Loan Tong, APRN",
      "Notes to Pharmacist: *Reorder from",
      "Notes: chronic, controlled",
      "Notes: chronic. stable, no o2 dependent.",
      "Ambien 5 mg Tab , Notes to",
      "Notes: chronic",
      "Notes: chronic, controlled",
      "oxyCODONE 5 mg Tab, Notes to",
      "MCG/INH Notes to Pharmacist:",
      "Notes: chronic, controlled,",
      "Diclofenac Sodium % Gel, Notes to",
      "Suspension, Notes to Pharmacist:",
      "Notes to Pharmacist: *Reorder from",
      "Lidocaine 5 % Patch Notes to",
      "Aerosol Solution Notes to Pharmacist:",
      "Sitagliptin Phosphate 100 MG, Notes",
      "Notes to Pharmacist: *Reorder from",
      "Notes: will refer to home health for PT",
      "Telmisartan 40 mg Tab, Notes to",
      "Meclizine 12.5 mg Tab Notes to",
      "Morphine Sulfate 15 mg Tab Notes to",
      "Erythromycin 5 mg/GM Oint , Notes to",
      "Notes: chronic, stable",
      "Notes to Pharmacist: *Reorder from",
      "Notes to Pharmacist: *Reorder from",
      "Mupirocin 2% Oint , Notes to",
      "Januvia 100 mg Tab Notes to",
      "Notes to Pharmacist: *Reorder from",
      "Notes to Pharmacist: *Reorder from",
      "Zolpidem Tartrate 5 mg Tab, Notes to",
      "Tab, Notes to Pharmacist: *Reorder",
      "Escitalopram Oxalate 5 mg Tab Notes",
      "Celecoxib 200 mg Cap Notes to",
      "Sublingual Notes to Pharmacist:",
      "Tab, Notes to Pharmacist: *Reorder",
      "Progress Note: Ngoc Loan Tong, APRN 01/15/2026",
      "Note generated by eClinicalWorks EMR/PM Software (www.eClinicalWorks.com)",
      "Notes Added On",
      "Not-Taking oxyCODONE-Acetaminophen 5/325 mg Tab Sig: Start Date: 08/12/2021, Notes: *Reorder from Medispan for eRx",
      "Not-Taking Zolpidem Tartrate 1.75 mg Tab Sublingual Sig: Start Date: 12/21/2021, Notes: *Reorder from Medispan for eRx and",
      "Not-Taking Celecoxib 200 mg Cap Sig: Start Date: 06/29/2020, Notes: *Reorder from Medispan for eRx and Interaction Alerts*",
      "Not-Taking Escitalopram Oxalate 5 mg Tab Sig: Start Date: 11/02/2020, Notes: *Reorder from Medispan for eRx and Interaction",
      "Not-Taking Cholecalciferol 1.25 mg (50000 UT) Tab, Sig: Start Date: 02/04/2021, Notes: *Reorder from Medispan for eRx and",
      "Not-Taking Zolpidem Tartrate 5 mg Tab, Sig: Start Date: 01/23/2023, Notes: *Reorder from Medispan for eRx and Interaction",
      "Not-Taking Omeprazole 20 mg Tab delayed rel, Sig: Start Date: 02/04/2021, Notes: *Reorder from Medispan for eRx and",
      "Not-Taking QUEtiapine Fumarate 25 mg Tab, Sig: Start Date: 12/24/2020, Notes: *Reorder from Medispan for eRx and",
      "Not-Taking Januvia 100 mg Tab, Sig: Start Date: 07/27/2020, Notes: *Reorder from Medispan for eRx and Interaction Alerts*",
      "Not-Taking Mupirocin 2% Oint, Sig: Start Date: 07/27/2020, Notes: *Reorder from Medispan for eRx and Interaction Alerts*",
      "Not-Taking Fluzone High-Dose Quadrivalent 0.7 ML Suspension Prefilled Syringe Sig: Start Date: 09/25/2020, Notes: *Reorder",
      "Not-Taking Alendronate Sodium 70 mg Tab, Sig: Start Date: 11/03/2020, Notes: *Reorder from Medispan for eRx and Interaction",
      "Not-Taking Erythromycin 5 mg/GM Oint, Sig: Start Date: 02/14/2023, Notes: *Reorder from Medispan for eRx and Interaction",
      "Not-Taking Morphine Sulfate 15 mg Tab, Sig: Start Date: 09/09/2021, Notes: *Reorder from Medispan for eRx and Interaction",
      "Not-Taking Meclizine 12.5 mg Tab, Sig: Start Date: 05/20/2021, Notes: *Reorder from Medispan for eRx and Interaction Alerts*",
      "Not-Taking Telmisartan 40 mg Tab, Sig: Start Date: 07/27/2020, Notes: *Reorder from Medispan for eRx and Interaction Alerts*",
      "Not-Taking Oseltamivir Phosphate 75 mg Cap, Sig: Start Date: 08/18/2020, Notes: *Reorder from Medispan for eRx and",
      "Not-Taking Sitagliptin Phosphate 100 MG, Sig: Start Date: 02/04/2021, Notes: *Reorder from Medispan for eRx and Interaction",
      "Not-Taking ProAir HFA 108 (90 Base) MCG/ACT Aerosol Solution Sig: Start Date: 08/18/2020, Notes: *Reorder from Medispan",
      "Not-Taking Lidocaine 5% Patch, Sig: Start Date: 05/12/2021, Notes: *Reorder from Medispan for eRx and Interaction Alerts*",
      "Not-Taking Mucinex DM 30/600 mg Tab ER 12hr, Sig: Start Date: 01/18/2023, Notes: *Reorder from Medispan for eRx and",
      "Not-Taking prednisoLONE Acetate 1 % Suspension Sig: Start Date: 08/02/2022, Notes: *Reorder from Medispan for eRx and",
      "Not-Taking Diclofenac Sodium 1 % Gel, Sig: Start Date: 02/28/2023, Notes: *Reorder from Medispan for eRx and Interaction",
      "Not-Taking Umeclidinium-Vilanterol 62.5-25 MCG/INH Sig: Start Date: 02/04/2021, Notes: *Reorder from Medispan for eRx and",
      "Not-Taking oxyCODONE 5 mg Tab, Sig: Start Date: 12/02/2022, Notes: *Reorder from Medispan for eRx and Interaction Alerts*",
      "Not-Taking Ambien 5 mg Tab, Sig: Start Date: 02/14/2022, Notes: *Reorder from Medispan for eRx and Interaction Alerts*",
      "Taking Anoro Ellipta 62.5-25 MCG/ACT Aerosol Powder Breath Activated , Sig: Start Date: 01/18/2023, Notes: *Reorder from",
      "Notes"
    ],
    "normalizedSummary": "Progress Note Progress Note: Ngoc Loan Tong, APRN Notes to Pharmacist: *Reorder from",
    "confidence": 1,
    "lineReferences": [
      {
        "lineStart": 163,
        "lineEnd": 163,
        "charStart": 3415,
        "charEnd": 3428
      },
      {
        "lineStart": 177,
        "lineEnd": 177,
        "charStart": 3731,
        "charEnd": 3766
      },
      {
        "lineStart": 193,
        "lineEnd": 193,
        "charStart": 4094,
        "charEnd": 4128
      },
      {
        "lineStart": 239,
        "lineEnd": 239,
        "charStart": 5388,
        "charEnd": 5414
      },
      {
        "lineStart": 260,
        "lineEnd": 260,
        "charStart": 6060,
        "charEnd": 6100
      },
      {
        "lineStart": 263,
        "lineEnd": 263,
        "charStart": 6176,
        "charEnd": 6202
      },
      {
        "lineStart": 281,
        "lineEnd": 281,
        "charStart": 6756,
        "charEnd": 6770
      },
      {
        "lineStart": 308,
        "lineEnd": 308,
        "charStart": 7663,
        "charEnd": 7689
      },
      {
        "lineStart": 311,
        "lineEnd": 311,
        "charStart": 7743,
        "charEnd": 7771
      },
      {
        "lineStart": 325,
        "lineEnd": 325,
        "charStart": 8209,
        "charEnd": 8237
      },
      {
        "lineStart": 327,
        "lineEnd": 327,
        "charStart": 8273,
        "charEnd": 8300
      },
      {
        "lineStart": 330,
        "lineEnd": 330,
        "charStart": 8357,
        "charEnd": 8390
      },
      {
        "lineStart": 337,
        "lineEnd": 337,
        "charStart": 8567,
        "charEnd": 8599
      },
      {
        "lineStart": 345,
        "lineEnd": 345,
        "charStart": 8810,
        "charEnd": 8844
      },
      {
        "lineStart": 353,
        "lineEnd": 353,
        "charStart": 9035,
        "charEnd": 9063
      },
      {
        "lineStart": 363,
        "lineEnd": 363,
        "charStart": 9390,
        "charEnd": 9427
      },
      {
        "lineStart": 369,
        "lineEnd": 369,
        "charStart": 9572,
        "charEnd": 9607
      },
      {
        "lineStart": 375,
        "lineEnd": 375,
        "charStart": 9823,
        "charEnd": 9857
      },
      {
        "lineStart": 379,
        "lineEnd": 379,
        "charStart": 9909,
        "charEnd": 9948
      },
      {
        "lineStart": 380,
        "lineEnd": 380,
        "charStart": 9949,
        "charEnd": 9980
      },
      {
        "lineStart": 386,
        "lineEnd": 386,
        "charStart": 10144,
        "charEnd": 10174
      },
      {
        "lineStart": 392,
        "lineEnd": 392,
        "charStart": 10327,
        "charEnd": 10362
      },
      {
        "lineStart": 397,
        "lineEnd": 397,
        "charStart": 10450,
        "charEnd": 10486
      },
      {
        "lineStart": 404,
        "lineEnd": 404,
        "charStart": 10737,
        "charEnd": 10759
      },
      {
        "lineStart": 411,
        "lineEnd": 411,
        "charStart": 10993,
        "charEnd": 11027
      },
      {
        "lineStart": 418,
        "lineEnd": 418,
        "charStart": 11161,
        "charEnd": 11195
      },
      {
        "lineStart": 424,
        "lineEnd": 424,
        "charStart": 11315,
        "charEnd": 11343
      },
      {
        "lineStart": 429,
        "lineEnd": 429,
        "charStart": 11492,
        "charEnd": 11519
      },
      {
        "lineStart": 440,
        "lineEnd": 440,
        "charStart": 11807,
        "charEnd": 11841
      },
      {
        "lineStart": 447,
        "lineEnd": 447,
        "charStart": 12061,
        "charEnd": 12095
      },
      {
        "lineStart": 452,
        "lineEnd": 452,
        "charStart": 12202,
        "charEnd": 12238
      },
      {
        "lineStart": 459,
        "lineEnd": 459,
        "charStart": 12512,
        "charEnd": 12546
      },
      {
        "lineStart": 468,
        "lineEnd": 468,
        "charStart": 12737,
        "charEnd": 12772
      },
      {
        "lineStart": 473,
        "lineEnd": 473,
        "charStart": 12935,
        "charEnd": 12964
      },
      {
        "lineStart": 482,
        "lineEnd": 482,
        "charStart": 13249,
        "charEnd": 13280
      },
      {
        "lineStart": 489,
        "lineEnd": 489,
        "charStart": 13489,
        "charEnd": 13523
      },
      {
        "lineStart": 679,
        "lineEnd": 679,
        "charStart": 17610,
        "charEnd": 17656
      },
      {
        "lineStart": 680,
        "lineEnd": 680,
        "charStart": 17657,
        "charEnd": 17730
      },
      {
        "lineStart": 715,
        "lineEnd": 715,
        "charStart": 18460,
        "charEnd": 18474
      },
      {
        "lineStart": 971,
        "lineEnd": 971,
        "charStart": 24503,
        "charEnd": 24617
      },
      {
        "lineStart": 974,
        "lineEnd": 974,
        "charStart": 24713,
        "charEnd": 24835
      },
      {
        "lineStart": 977,
        "lineEnd": 977,
        "charStart": 24939,
        "charEnd": 25061
      },
      {
        "lineStart": 978,
        "lineEnd": 978,
        "charStart": 25062,
        "charEnd": 25185
      },
      {
        "lineStart": 985,
        "lineEnd": 985,
        "charStart": 25450,
        "charEnd": 25571
      },
      {
        "lineStart": 987,
        "lineEnd": 987,
        "charStart": 25592,
        "charEnd": 25713
      },
      {
        "lineStart": 989,
        "lineEnd": 989,
        "charStart": 25722,
        "charEnd": 25837
      },
      {
        "lineStart": 991,
        "lineEnd": 991,
        "charStart": 25858,
        "charEnd": 25970
      },
      {
        "lineStart": 993,
        "lineEnd": 993,
        "charStart": 25991,
        "charEnd": 26112
      },
      {
        "lineStart": 995,
        "lineEnd": 995,
        "charStart": 26199,
        "charEnd": 26319
      },
      {
        "lineStart": 997,
        "lineEnd": 997,
        "charStart": 26402,
        "charEnd": 26524
      },
      {
        "lineStart": 999,
        "lineEnd": 999,
        "charStart": 26571,
        "charEnd": 26694
      },
      {
        "lineStart": 1002,
        "lineEnd": 1002,
        "charStart": 26815,
        "charEnd": 26935
      },
      {
        "lineStart": 1004,
        "lineEnd": 1004,
        "charStart": 26944,
        "charEnd": 27065
      },
      {
        "lineStart": 1006,
        "lineEnd": 1006,
        "charStart": 27074,
        "charEnd": 27198
      },
      {
        "lineStart": 1008,
        "lineEnd": 1008,
        "charStart": 27272,
        "charEnd": 27396
      },
      {
        "lineStart": 1009,
        "lineEnd": 1009,
        "charStart": 27397,
        "charEnd": 27511
      },
      {
        "lineStart": 1011,
        "lineEnd": 1011,
        "charStart": 27532,
        "charEnd": 27655
      },
      {
        "lineStart": 1013,
        "lineEnd": 1013,
        "charStart": 27664,
        "charEnd": 27783
      },
      {
        "lineStart": 1016,
        "lineEnd": 1016,
        "charStart": 27907,
        "charEnd": 28028
      },
      {
        "lineStart": 1017,
        "lineEnd": 1017,
        "charStart": 28029,
        "charEnd": 28144
      },
      {
        "lineStart": 1019,
        "lineEnd": 1019,
        "charStart": 28165,
        "charEnd": 28282
      },
      {
        "lineStart": 1021,
        "lineEnd": 1021,
        "charStart": 28303,
        "charEnd": 28423
      },
      {
        "lineStart": 1023,
        "lineEnd": 1023,
        "charStart": 28432,
        "charEnd": 28553
      },
      {
        "lineStart": 1027,
        "lineEnd": 1027,
        "charStart": 28684,
        "charEnd": 28805
      },
      {
        "lineStart": 1039,
        "lineEnd": 1039,
        "charStart": 29666,
        "charEnd": 29784
      },
      {
        "lineStart": 1051,
        "lineEnd": 1051,
        "charStart": 30640,
        "charEnd": 30760
      },
      {
        "lineStart": 1256,
        "lineEnd": 1256,
        "charStart": 33134,
        "charEnd": 33139
      }
    ]
  }
]