{
  "id": "schedule-batch-aplus-home-health-2026-04-22T19-22-03-641Z-181197f4",
  "subsidiaryId": "aplus-home-health",
  "batchId": "batch-aplus-home-health-2026-04-22T19-22-03-641Z-181197f4",
  "workbookPath": "C:\\dev\\medical-aq-qa\\services\\api\\data\\control-plane\\batches\\aplus-home-health\\batch-aplus-home-health-2026-04-22T19-22-03-641Z-181197f4\\source\\aplus-home-health-oasis-30-days.xlsx",
  "originalFileName": "OASIS Tracking (30 Days Tracking).xlsx",
  "active": false,
  "rerunEnabled": false,
  "intervalHours": 24,
  "timezone": "Asia/Manila",
  "localTimes": [
    "15:00",
    "23:30"
  ],
  "lastRunAt": "2026-04-22T20:21:33.220Z",
  "nextScheduledRunAt": null,
  "createdAt": "2026-04-22T19:22:03.642Z",
  "updatedAt": "2026-04-22T20:21:33.220Z"
}